ior_parser/__init__.py
ior_parser/__main__.py
ior_parser/parser.py
ior_parser/utils.py
ior_parser-0.1.1.dist-info/METADATA
ior_parser-0.1.1.dist-info/WHEEL
ior_parser-0.1.1.dist-info/entry_points.txt
ior_parser-0.1.1.dist-info/licenses/LICENSE
ior_parser-0.1.1.dist-info/RECORD
