Metadata-Version: 2.4
Name: ior-parser
Version: 0.1.1
Summary: IOR benchmark log file parser for performance analysis and comparison
Project-URL: Homepage, https://github.com/izzet/ior-parser
Project-URL: Repository, https://github.com/izzet/ior-parser
Project-URL: Documentation, https://github.com/izzet/ior-parser#readme
Project-URL: Bug Tracker, https://github.com/izzet/ior-parser/issues
Author-email: Izzet Yildirim <izzetcyildirim@gmail.com>
Maintainer-email: Izzet Yildirim <izzetcyildirim@gmail.com>
License: MIT
License-File: LICENSE
Keywords: analysis,benchmark,hpc,ior,parser,performance
Classifier: Development Status :: 4 - Beta
Classifier: Intended Audience :: Developers
Classifier: Intended Audience :: Science/Research
Classifier: License :: OSI Approved :: MIT License
Classifier: Programming Language :: Python :: 3
Classifier: Programming Language :: Python :: 3.8
Classifier: Programming Language :: Python :: 3.9
Classifier: Programming Language :: Python :: 3.10
Classifier: Programming Language :: Python :: 3.11
Classifier: Programming Language :: Python :: 3.12
Classifier: Topic :: Scientific/Engineering
Classifier: Topic :: Software Development :: Libraries :: Python Modules
Classifier: Topic :: System :: Benchmark
Classifier: Topic :: Utilities
Requires-Python: >=3.8
